nlp_structgen/__init__.py
nlp_structgen/main.py
nlp_structgen/prompts.py
nlp_structgen-2025.12.20202749.dist-info/METADATA
nlp_structgen-2025.12.20202749.dist-info/WHEEL
nlp_structgen-2025.12.20202749.dist-info/top_level.txt
nlp_structgen-2025.12.20202749.dist-info/RECORD
