Metadata-Version: 2.4
Name: nlp-structgen
Version: 2025.12.20202749
Summary: Structured TextOutcome Generator: A scalable, instance-and company-specific knowledge base and language model-powered solution that uses Natural Language Processing (NLP), Machine Learning (ML) and Hu
Author-email: nlp-structgen <hi@eugene.plus>
License: MIT
Project-URL: Homepage, https://github.com/chigwell/nlp-structgen
Requires-Python: >=3.9
Requires-Dist: langchain-llm7>=0.0.0
Requires-Dist: llmatch-messages>=0.0.0
Requires-Dist: langchain-core>=0.3.0
